UART-04/uart_rx.sv
module uart_rx (
    input logic clk,
    input logic rst,
    input logic rx,

    output logic data_valid,
    output logic [7:0] data
);

  typedef enum {
    IDLE,
    START,
    DATA,
    STOP
  } state_t;

  logic [6:0] baud_counter;
  logic baud_tick;
  logic [3:0] tick_counter;

  logic [2:0] bit_index;
  logic [7:0] data_shifter;

  assign baud_tick = (baud_counter == 77);

  state_t current_state;

  always_ff @(posedge clk) begin
    if (rst) begin
      current_state <= IDLE;
      bit_index <= 7;
      tick_counter <= 0;
      data_shifter <= 0;
      baud_counter <= 0;
    end else begin
      if (baud_tick) baud_counter <= 0;
      else baud_counter <= baud_counter + 1;

      if (baud_tick) begin
        case (current_state)
          IDLE: begin
            if (rx == 0) begin
              current_state <= START;
              tick_counter <= 0;
              bit_index <= 7;
            end
          end
          START: begin
            if (tick_counter == 7) begin
              current_state <= DATA;
            end
            tick_counter <= tick_counter + 1;
          end
          DATA: begin
            if (tick_counter == 15) begin
              data_shifter[bit_index] <= rx;
              tick_counter <= 0;
              if (bit_index == 0) begin
                current_state <= STOP;
              end else begin
                current_state <= DATA;
                bit_index <= bit_index - 1;
              end
            end else begin
              tick_counter <= tick_counter + 1;
            end
          end
          STOP: begin
            if (tick_counter == 15) begin
              current_state <= IDLE;
              data <= data_shifter;
              data_valid <= 1'b1;
              tick_counter <= 0;
            end else begin
              tick_counter <= tick_counter + 1;
            end
          end
          default: current_state <= IDLE;
        endcase
      end else begin
        data_valid <= 1'b0;
      end
    end
  end


endmodule

UART-04/uart_tx.sv
module uart_tx (
    input logic clk,
    input logic rst,
    input logic [7:0] data,
    input logic send,
    output logic tx
);

  logic [6:0] baud_counter;
  logic [3:0] tick_counter;
  logic baud_tick;
  logic [7:0] data_register;
  logic [2:0] bit_index;

  typedef enum {
    IDLE,
    START,
    DATA,
    STOP
  } state_t;

  state_t current_state;
  state_t next_state;

  assign baud_tick = (baud_counter == 77);

  always_comb begin
    next_state = current_state;
    case (current_state)
      IDLE: begin
        tx = 1;
        if (send) next_state = START;
      end
      START: begin
        tx = 0;
        if (baud_tick && (tick_counter == 15)) next_state = DATA;
      end
      DATA: begin
        tx = data_register[bit_index];
        if (baud_tick && (tick_counter == 15)) begin
          if (bit_index == 7) next_state = STOP;
          else next_state = DATA;
        end
      end
      STOP: begin
        tx = 1;
        if (baud_tick && (tick_counter == 15)) next_state = IDLE;
      end
      default: next_state = IDLE;
    endcase
  end

  always_ff @(posedge clk) begin
    if (rst) begin
      current_state <= IDLE;
      baud_counter <= 0;
      tick_counter <= 0;
      data_register <= 0;
      bit_index <= 0;
    end else begin
      current_state <= next_state;

      if (baud_tick) baud_counter <= 0;
      else baud_counter <= baud_counter + 1;

      if (current_state == IDLE) begin
        bit_index <= 0;
        tick_counter <= 0;
        if (send) begin
          data_register <= data;
        end
      end

      if (baud_tick) begin
        if (tick_counter == 15) begin
          tick_counter <= 0;
          if (current_state == DATA) bit_index <= bit_index + 1;
        end else begin
          tick_counter <= tick_counter + 1;
        end
      end
    end
  end

endmodule

UART-04/tb_uart.sv
`timescale 1ns / 1ps

module tb_uart;

  // Clock & Reset
  logic clk;
  logic rst;

  // Interconnects
  logic [7:0] tx_data;
  logic tx_send;
  logic tx_to_rx_line;  // Direct wire from TX to RX

  logic rx_data_valid;
  logic [7:0] rx_data;

  // Instantiate Transmitter
  uart_tx tx_inst (
      .clk (clk),
      .rst (rst),
      .data(tx_data),
      .send(tx_send),
      .tx  (tx_to_rx_line)
  );

  // Instantiate Receiver
  uart_rx rx_inst (
      .clk       (clk),
      .rst       (rst),
      .rx        (tx_to_rx_line),
      .data_valid(rx_data_valid),
      .data      (rx_data)
  );

  // Create 50MHz Clock (20ns period)
  always begin
    #10 clk = ~clk;
  end

  // Clean Task to handle byte transmission
  task automatic send_byte(input logic [7:0] data_byte);
    begin
      @(posedge clk);
      tx_data = data_byte;
      tx_send = 1;
      @(posedge clk);
      tx_send = 0;

      // Wait for complete 10-bit frame (12,480 cycles total)
      repeat (13000) @(posedge clk);

      // Extra breathing room between packets (approx 200 cycles)
      repeat (200) @(posedge clk);
    end
  endtask

  // Simulation Sequence
  initial begin
    // Setup for GTKWave waveform collection
    $dumpfile("uart_waves.vcd");
    $dumpvars(0, tb_uart);

    // Initial State Configuration
    clk = 0;
    rst = 1;
    tx_data = 8'h00;
    tx_send = 0;

    // Hold Reset
    repeat (10) @(posedge clk);
    rst = 0;
    repeat (5) @(posedge clk);

    $display("[TB] --- Starting Clean UART Simulation ---");

    // Send 3 distinct test bytes sequentially
    $display("[TB] Sending Byte 1: 8'hAC");
    send_byte(8'hAC);

    $display("[TB] Sending Byte 2: 8'h55");
    send_byte(8'h55);

    $display("[TB] Sending Byte 3: 8'hF0");
    send_byte(8'hF0);

    repeat (500) @(posedge clk);
    $display("[TB] --- Simulation Run Completed ---");
    $finish;
  end

  // Monitor Terminal Output Block
  always @(posedge clk) begin
    if (rx_data_valid) begin
      $display("[TB MONITOR] Received Byte = 8'h%h", rx_data);
    end
  end

endmodule

UART-04/uart_waves.vcd
$date
	Thu Jun 11 23:19:55 2026
$end
$version
	Icarus Verilog
$end
$timescale
	1ps
$end
$scope module tb_uart $end
$var wire 1 ! tx_to_rx_line $end
$var wire 1 " rx_data_valid $end
$var wire 8 # rx_data [7:0] $end
$var reg 1 $ clk $end
$var reg 1 % rst $end
$var reg 8 & tx_data [7:0] $end
$var reg 1 ' tx_send $end
$scope module rx_inst $end
$var wire 1 $ clk $end
$var wire 1 % rst $end
$var wire 1 ! rx $end
$var wire 1 ( baud_tick $end
$var reg 7 ) baud_counter [6:0] $end
$var reg 3 * bit_index [2:0] $end
$var reg 8 + data [7:0] $end
$var reg 8 , data_shifter [7:0] $end
$var reg 1 " data_valid $end
$var reg 4 - tick_counter [3:0] $end
$var integer 32 . current_state [31:0] $end
$upscope $end
$scope module tx_inst $end
$var wire 1 $ clk $end
$var wire 8 / data [7:0] $end
$var wire 1 % rst $end
$var wire 1 ' send $end
$var wire 1 0 baud_tick $end
$var reg 7 1 baud_counter [6:0] $end
$var reg 3 2 bit_index [2:0] $end
$var reg 8 3 data_register [7:0] $end
$var reg 4 4 tick_counter [3:0] $end
$var reg 1 ! tx $end
$var integer 32 5 current_state [31:0] $end
$var integer 32 6 next_state [31:0] $end
$upscope $end
$scope task send_byte $end
$upscope $end
$upscope $end
$enddefinitions $end
$comment Show the parameter values. $end
$dumpall
$end
#0
$dumpvars
b0 6
b0 5
bx 4
bx 3
bx 2
bx 1
x0
b0 /
b0 .
bx -
bx ,
bx +
bx *
bx )
x(
0'
b0 &
1%
0$
bx #
x"
1!
$end
#10000
00
0(
b0 2
b0 3
b0 4
b0 1
0"
b0 )
b0 ,
b0 -
b0 *
1$
#20000
0$
#30000
1$
#40000
0$
#50000
1$
#60000
0$
#70000
1$
#80000
0$
#90000
1$
#100000
0$
#110000
1$
#120000
0$
#130000
1$
#140000
0$
#150000
1$
#160000
0$
#170000
1$
#180000
0$
#190000
0%
1$
#200000
0$
#210000
b1 1
b1 )
1$
#220000
0$
#230000
b10 )
b10 1
1$
#240000
0$
#250000
b11 1
b11 )
1$
#260000
0$
#270000
b100 )
b100 1
1$
#280000
0$
#290000
b101 1
b101 )
1$
#300000
0$
#310000
b110 )
b10101100 3
b110 1
b1 6
1'
b10101100 &
b10101100 /
1$
#320000
0$
#330000
0!
b111 1
b1 5
b111 )
b1 6
0'
1$
#340000
0$
#350000
b1000 )
b1000 1
1$
#360000
0$
#370000
b1001 1
b1001 )
1$
#380000
0$
#390000
b1010 )
b1010 1
1$
#400000
0$
#410000
b1011 1
b1011 )
1$
#420000
0$
#430000
b1100 )
b1100 1
1$
#440000
0$
#450000
b1101 1
b1101 )
1$
#460000
0$
#470000
b1110 )
b1110 1
1$
#480000
0$
#490000
b1111 1
b1111 )
1$
#500000
0$
#510000
b10000 )
b10000 1
1$
#520000
0$
#530000
b10001 1
b10001 )
1$
#540000
0$
#550000
b10010 )
b10010 1
1$
#560000
0$
#570000
b10011 1
b10011 )
1$
#580000
0$
#590000
b10100 )
b10100 1
1$
#600000
0$
#610000
b10101 1
b10101 )
1$
#620000
0$
#630000
b10110 )
b10110 1
1$
#640000
0$
#650000
b10111 1
b10111 )
1$
#660000
0$
#670000
b11000 )
b11000 1
1$
#680000
0$
#690000
b11001 1
b11001 )
1$
#700000
0$
#710000
b11010 )
b11010 1
1$
#720000
0$
#730000
b11011 1
b11011 )
1$
#740000
0$
#750000
b11100 )
b11100 1
1$
#760000
0$
#770000
b11101 1
b11101 )
1$
#780000
0$
#790000
b11110 )
b11110 1
1$
#800000
0$
#810000
b11111 1
b11111 )
1$
#820000
0$
#830000
b100000 )
b100000 1
1$
#840000
0$
#850000
b100001 1
b100001 )
1$
#860000
0$
#870000
b100010 )
b100010 1
1$
#880000
0$
#890000
b100011 1
b100011 )
1$
#900000
0$
#910000
b100100 )
b100100 1
1$
#920000
0$
#930000
b100101 1
b100101 )
1$
#940000
0$
#950000
b100110 )
b100110 1
1$
#960000
0$
#970000
b100111 1
b100111 )
1$
#980000
0$
#990000
b101000 )
b101000 1
1$
#1000000
0$
#1010000
b101001 1
b101001 )
1$
#1020000
0$
#1030000
b101010 )
b101010 1
1$
#1040000
0$
#1050000
b101011 1
b101011 )
1$
#1060000
0$
#1070000
b101100 )
b101100 1
1$
#1080000
0$
#1090000
b101101 1
b101101 )
1$
#1100000
0$
#1110000
b101110 )
b101110 1
1$
#1120000
0$
#1130000
b101111 1
b101111 )
1$
#1140000
0$
#1150000
b110000 )
b110000 1
1$
#1160000
0$
#1170000
b110001 1
b110001 )
1$
#1180000
0$
#1190000
b110010 )
b110010 1
1$
#1200000
0$
#1210000
b110011 1
b110011 )
1$
#1220000
0$
#1230000
b110100 )
b110100 1
1$
#1240000
0$
#1250000
b110101 1
b110101 )
1$
#1260000
0$
#1270000
b110110 )
b110110 1
1$
#1280000
0$
#1290000
b110111 1
b110111 )
1$
#1300000
0$
#1310000
b111000 )
b111000 1
1$
#1320000
0$
#1330000
b111001 1
b111001 )
1$
#1340000
0$
#1350000
b111010 )
b111010 1
1$
#1360000
0$
#1370000
b111011 1
b111011 )
1$
#1380000
0$
#1390000
b111100 )
b111100 1
1$
#1400000
0$
#1410000
b111101 1
b111101 )
1$
#1420000
0$
#1430000
b111110 )
b111110 1
1$
#1440000
0$
#1450000
b111111 1
b111111 )
1$
#1460000
0$
#1470000
b1000000 )
b1000000 1
1$
#1480000
0$
#1490000
b1000001 1
b1000001 )
1$
#1500000
0$
#1510000
b1000010 )
b1000010 1
1$
#1520000
0$
#1530000
b1000011 1
b1000011 )
1$
#1540000
0$
#1550000
b1000100 )
b1000100 1
1$
#1560000
0$
#1570000
b1000101 1
b1000101 )
1$
#1580000
0$
#1590000
b1000110 )
b1000110 1
1$
#1600000
0$
#1610000
b1000111 1
b1000111 )
1$
#1620000
0$
#1630000
b1001000 )
b1001000 1
1$
#1640000
0$
#1650000
b1001001 1
b1001001 )
1$
#1660000
0$
#1670000
b1001010 )
b1001010 1
1$
#1680000
0$
#1690000
b1001011 1
b1001011 )
1$
#1700000
0$
#1710000
b1001100 )
b1001100 1
1$
#1720000
0$
#1730000
10
1(
b1001101 1
b1001101 )
1$
#1740000
0$
#1750000
0(
00
b1 .
b0 )
b1 4
b0 1
1$
#1760000
0$
#1770000
b1 1
b1 )
1$
#1780000
0$
#1790000
b10 )
b10 1
1$
#1800000
0$
#1810000
b11 1
b11 )
1$
#1820000
0$
#1830000
b100 )
b100 1
1$
#1840000
0$
#1850000
b101 1
b101 )
1$
#1860000
0$
#1870000
b110 )
b110 1
1$
#1880000
0$
#1890000
b111 1
b111 )
1$
#1900000
0$
#1910000
b1000 )
b1000 1
1$
#1920000
0$
#1930000
b1001 1
b1001 )
1$
#1940000
0$
#1950000
b1010 )
b1010 1
1$
#1960000
0$
#1970000
b1011 1
b1011 )
1$
#1980000
0$
#1990000
b1100 )
b1100 1
1$
#2000000
0$
#2010000
b1101 1
b1101 )
1$
#2020000
0$
#2030000
b1110 )
b1110 1
1$
#2040000
0$
#2050000
b1111 1
b1111 )
1$
#2060000
0$
#2070000
b10000 )
b10000 1
1$
#2080000
0$
#2090000
b10001 1
b10001 )
1$
#2100000
0$
#2110000
b10010 )
b10010 1
1$
#2120000
0$
#2130000
b10011 1
b10011 )
1$
#2140000
0$
#2150000
b10100 )
b10100 1
1$
#2160000
0$
#2170000
b10101 1
b10101 )
1$
#2180000
0$
#2190000
b10110 )
b10110 1
1$
#2200000
0$
#2210000
b10111 1
b10111 )
1$
#2220000
0$
#2230000
b11000 )
b11000 1
1$
#2240000
0$
#2250000
b11001 1
b11001 )
1$
#2260000
0$
#2270000
b11010 )
b11010 1
1$
#2280000
0$
#2290000
b11011 1
b11011 )
1$
#2300000
0$
#2310000
b11100 )
b11100 1
1$
#2320000
0$
#2330000
b11101 1
b11101 )
1$
#2340000
0$
#2350000
b11110 )
b11110 1
1$
#2360000
0$
#2370000
b11111 1
b11111 )
1$
#2380000
0$
#2390000
b100000 )
b100000 1
1$
#2400000
0$
#2410000
b100001 1
b100001 )
1$
#2420000
0$
#2430000
b100010 )
b100010 1
1$
#2440000
0$
#2450000
b100011 1
b100011 )
1$
#2460000
0$
#2470000
b100100 )
b100100 1
1$
#2480000
0$
#2490000
b100101 1
b100101 )
1$
#2500000
0$
#2510000
b100110 )
b100110 1
1$
#2520000
0$
#2530000
b100111 1
b100111 )
1$
#2540000
0$
#2550000
b101000 )
b101000 1
1$
#2560000
0$
#2570000
b101001 1
b101001 )
1$
#2580000
0$
#2590000
b101010 )
b101010 1
1$
#2600000
0$
#2610000
b101011 1
b101011 )
1$
#2620000
0$
#2630000
b101100 )
b101100 1
1$
#2640000
0$
#2650000
b101101 1
b101101 )
1$
#2660000
0$
#2670000
b101110 )
b101110 1
1$
#2680000
0$
#2690000
b101111 1
b101111 )
1$
#2700000
0$
#2710000
b110000 )
b110000 1
1$
#2720000
0$
#2730000
b110001 1
b110001 )
1$
#2740000
0$
#2750000
b110010 )
b110010 1
1$
#2760000
0$
#2770000
b110011 1
b110011 )
1$
#2780000
0$
#2790000
b110100 )
b110100 1
1$
#2800000
0$
#2810000
b110101 1
b110101 )
1$
#2820000
0$
#2830000
b110110 )
b110110 1
1$
#2840000
0$
#2850000
b110111 1
b110111 )
1$
#2860000
0$
#2870000
b111000 )
b111000 1
1$
#2880000
0$
#2890000
b111001 1
b111001 )
1$
#2900000
0$
#2910000
b111010 )
b111010 1
1$
#2920000
0$
#2930000
b111011 1
b111011 )
1$
#2940000
0$
#2950000
b111100 )
b111100 1
1$
#2960000
0$
#2970000
b111101 1
b111101 )
1$
#2980000
0$
#2990000
b111110 )
b111110 1
1$
#3000000
0$
#3010000
b111111 1
b111111 )
1$
#3020000
0$
#3030000
b1000000 )
b1000000 1
1$
#3040000
0$
#3050000
b1000001 1
b1000001 )
1$
#3060000
0$
#3070000
b1000010 )
b1000010 1
1$
#3080000
0$
#3090000
b1000011 1
b1000011 )
1$
#3100000
0$
#3110000
b1000100 )
b1000100 1
1$
#3120000
0$
#3130000
b1000101 1
b1000101 )
1$
#3140000
0$
#3150000
b1000110 )
b1000110 1
1$
#3160000
0$
#3170000
b1000111 1
b1000111 )
1$
#3180000
0$
#3190000
b1001000 )
b1001000 1
1$
#3200000
0$
#3210000
b1001001 1
b1001001 )
1$
#3220000
0$
#3230000
b1001010 )
b1001010 1
1$
#3240000
0$
#3250000
b1001011 1
b1001011 )
1$
#3260000
0$
#3270000
b1001100 )
b1001100 1
1$
#3280000
0$
#3290000
10
1(
b1001101 1
b1001101 )
1$
#3300000
0$
#3310000
0(
00
b1 -
b0 )
b10 4
b0 1
1$
#3320000
0$
#3330000
b1 1
b1 )
1$
#3340000
0$
#3350000
b10 )
b10 1
1$
#3360000
0$
#3370000
b11 1
b11 )
1$
#3380000
0$
#3390000
b100 )
b100 1
1$
#3400000
0$
#3410000
b101 1
b101 )
1$
#3420000
0$
#3430000
b110 )
b110 1
1$
#3440000
0$
#3450000
b111 1
b111 )
1$
#3460000
0$
#3470000
b1000 )
b1000 1
1$
#3480000
0$
#3490000
b1001 1
b1001 )
1$
#3500000
0$
#3510000
b1010 )
b1010 1
1$
#3520000
0$
#3530000
b1011 1
b1011 )
1$
#3540000
0$
#3550000
b1100 )
b1100 1
1$
#3560000
0$
#3570000
b1101 1
b1101 )
1$
#3580000
0$
#3590000
b1110 )
b1110 1
1$
#3600000
0$
#3610000
b1111 1
b1111 )
1$
#3620000
0$
#3630000
b10000 )
b10000 1
1$
#3640000
0$
#3650000
b10001 1
b10001 )
1$
#3660000
0$
#3670000
b10010 )
b10010 1
1$
#3680000
0$
#3690000
b10011 1
b10011 )
1$
#3700000
0$
#3710000
b10100 )
b10100 1
1$
#3720000
0$
#3730000
b10101 1
b10101 )
1$
#3740000
0$
#3750000
b10110 )
b10110 1
1$
#3760000
0$
#3770000
b10111 1
b10111 )
1$
#3780000
0$
#3790000
b11000 )
b11000 1
1$
#3800000
0$
#3810000
b11001 1
b11001 )
1$
#3820000
0$
#3830000
b11010 )
b11010 1
1$
#3840000
0$
#3850000
b11011 1
b11011 )
1$
#3860000
0$
#3870000
b11100 )
b11100 1
1$
#3880000
0$
#3890000
b11101 1
b11101 )
1$
#3900000
0$
#3910000
b11110 )
b11110 1
1$
#3920000
0$
#3930000
b11111 1
b11111 )
1$
#3940000
0$
#3950000
b100000 )
b100000 1
1$
#3960000
0$
#3970000
b100001 1
b100001 )
1$
#3980000
0$
#3990000
b100010 )
b100010 1
1$
#4000000
0$
#4010000
b100011 1
b100011 )
1$
#4020000
0$
#4030000
b100100 )
b100100 1
1$
#4040000
0$
#4050000
b100101 1
b100101 )
1$
#4060000
0$
#4070000
b100110 )
b100110 1
1$
#4080000
0$
#4090000
b100111 1
b100111 )
1$
#4100000
0$
#4110000
b101000 )
b101000 1
1$
#4120000
0$
#4130000
b101001 1
b101001 )
1$
#4140000
0$
#4150000
b101010 )
b101010 1
1$
#4160000
0$
#4170000
b101011 1
b101011 )
1$
#4180000
0$
#4190000
b101100 )
b101100 1
1$
#4200000
0$
#4210000
b101101 1
b101101 )
1$
#4220000
0$
#4230000
b101110 )
b101110 1
1$
#4240000
0$
#4250000
b101111 1
b101111 )
1$
#4260000
0$
#4270000
b110000 )
b110000 1
1$
#4280000
0$
#4290000
b110001 1
b110001 )
1$
#4300000
0$
#4310000
b110010 )
b110010 1
1$
#4320000
0$
#4330000
b110011 1
b110011 )
1$
#4340000
0$
#4350000
b110100 )
b110100 1
1$
#4360000
0$
#4370000
b110101 1
b110101 )
1$
#4380000
0$
#4390000
b110110 )
b110110 1
1$
#4400000
0$
#4410000
b110111 1
b110111 )
1$
#4420000
0$
#4430000
b111000 )
b111000 1
1$
#4440000
0$
#4450000
b111001 1
b111001 )
1$
#4460000
0$
#4470000
b111010 )
b111010 1
1$
#4480000
0$
#4490000
b111011 1
b111011 )
1$
#4500000
0$
#4510000
b111100 )
b111100 1
1$
#4520000
0$
#4530000
b111101 1
b111101 )
1$
#4540000
0$
#4550000
b111110 )
b111110 1
1$
#4560000
0$
#4570000
b111111 1
b111111 )
1$
#4580000
0$
#4590000
b1000000 )
b1000000 1
1$
#4600000
0$
#4610000
b1000001 1
b1000001 )
1$
#4620000
0$
#4630000
b1000010 )
b1000010 1
1$
#4640000
0$
#4650000
b1000011 1
b1000011 )
1$
#4660000
0$
#4670000
b1000100 )
b1000100 1
1$
#4680000
0$
#4690000
b1000101 1
b1000101 )
1$
#4700000
0$
#4710000
b1000110 )
b1000110 1
1$
#4720000
0$
#4730000
b1000111 1
b1000111 )
1$
#4740000
0$
#4750000
b1001000 )
b1001000 1
1$
#4760000
0$
#4770000
b1001001 1
b1001001 )
1$
#4780000
0$
#4790000
b1001010 )
b1001010 1
1$
#4800000
0$
#4810000
b1001011 1
b1001011 )
1$
#4820000
0$
#4830000
b1001100 )
b1001100 1
1$
#4840000
0$
#4850000
10
1(
b1001101 1
b1001101 )
1$
#4860000
0$
#4870000
0(
00
b10 -
b0 )
b11 4
b0 1
1$
#4880000
0$
#4890000
b1 1
b1 )
1$
#4900000
0$
#4910000
b10 )
b10 1
1$
#4920000
0$
#4930000
b11 1
b11 )
1$
#4940000
0$
#4950000
b100 )
b100 1
1$
#4960000
0$
#4970000
b101 1
b101 )
1$
#4980000
0$
#4990000
b110 )
b110 1
1$
#5000000
0$
#5010000
b111 1
b111 )
1$
#5020000
0$
#5030000
b1000 )
b1000 1
1$
#5040000
0$
#5050000
b1001 1
b1001 )
1$
#5060000
0$
#5070000
b1010 )
b1010 1
1$
#5080000
0$
#5090000
b1011 1
b1011 )
1$
#5100000
0$
#5110000
b1100 )
b1100 1
1$
#5120000
0$
#5130000
b1101 1
b1101 )
1$
#5140000
0$
#5150000
b1110 )
b1110 1
1$
#5160000
0$
#5170000
b1111 1
b1111 )
1$
#5180000
0$
#5190000
b10000 )
b10000 1
1$
#5200000
0$
#5210000
b10001 1
b10001 )
1$
#5220000
0$
#5230000
b10010 )
b10010 1
1$
#5240000
0$
#5250000
b10011 1
b10011 )
1$
#5260000
0$
#5270000
b10100 )
b10100 1
1$
#5280000
0$
#5290000
b10101 1
b10101 )
1$
#5300000
0$
#5310000
b10110 )
b10110 1
1$
#5320000
0$
#5330000
b10111 1
b10111 )
1$
#5340000
0$
#5350000
b11000 )
b11000 1
1$
#5360000
0$
#5370000
b11001 1
b11001 )
1$
#5380000
0$
#5390000
b11010 )
b11010 1
1$
#5400000
0$
#5410000
b11011 1
b11011 )
1$
#5420000
0$
#5430000
b11100 )
b11100 1
1$
#5440000
0$
#5450000
b11101 1
b11101 )
1$
#5460000
0$
#5470000
b11110 )
b11110 1
1$
#5480000
0$
#5490000
b11111 1
b11111 )
1$
#5500000
0$
#5510000
b100000 )
b100000 1
1$
#5520000
0$
#5530000
b100001 1
b100001 )
1$
#5540000
0$
#5550000
b100010 )
b100010 1
1$
#5560000
0$
#5570000
b100011 1
b100011 )
1$
#5580000
0$
#5590000
b100100 )
b100100 1
1$
#5600000
0$
#5610000
b100101 1
b100101 )
1$
#5620000
0$
#5630000
b100110 )
b100110 1
1$
#5640000
0$
#5650000
b100111 1
b100111 )
1$
#5660000
0$
#5670000
b101000 )
b101000 1
1$
#5680000
0$
#5690000
b101001 1
b101001 )
1$
#5700000
0$
#5710000
b101010 )
b101010 1
1$
#5720000
0$
#5730000
b101011 1
b101011 )
1$
#5740000
0$
#5750000
b101100 )
b101100 1
1$
#5760000
0$
#5770000
b101101 1
b101101 )
1$
#5780000
0$
#5790000
b101110 )
b101110 1
1$
#5800000
0$
#5810000
b101111 1
b101111 )
1$
#5820000
0$
#5830000
b110000 )
b110000 1
1$
#5840000
0$
#5850000
b110001 1
b110001 )
1$
#5860000
0$
#5870000
b110010 )
b110010 1
1$
#5880000
0$
#5890000
b110011 1
b110011 )
1$
#5900000
0$
#5910000
b110100 )
b110100 1
1$
#5920000
0$
#5930000
b110101 1
b110101 )
1$
#5940000
0$
#5950000
b110110 )
b110110 1
1$
#5960000
0$
#5970000
b110111 1
b110111 )
1$
#5980000
0$
#5990000
b111000 )
b111000 1
1$
#6000000
0$
#6010000
b111001 1
b111001 )
1$
#6020000
0$
#6030000
b111010 )
b111010 1
1$
#6040000
0$
#6050000
b111011 1
b111011 )
1$
#6060000
0$
#6070000
b111100 )
b111100 1
1$
#6080000
0$
#6090000
b111101 1
b111101 )
1$
#6100000
0$
#6110000
b111110 )
b111110 1
1$
#6120000
0$
#6130000
b111111 1
b111111 )
1$
#6140000
0$
#6150000
b1000000 )
b1000000 1
1$
#6160000
0$
#6170000
b1000001 1
b1000001 )
1$
#6180000
0$
#6190000
b1000010 )
b1000010 1
1$
#6200000
0$
#6210000
b1000011 1
b1000011 )
1$
#6220000
0$
#6230000
b1000100 )
b1000100 1
1$
#6240000
0$
#6250000
b1000101 1
b1000101 )
1$
#6260000
0$
#6270000
b1000110 )
b1000110 1
1$
#6280000
0$
#6290000
b1000111 1
b1000111 )
1$
#6300000
0$
#6310000
b1001000 )
b1001000 1
1$
#6320000
0$
#6330000
b1001001 1
b1001001 )
1$
#6340000
0$
#6350000
b1001010 )
b1001010 1
1$
#6360000
0$
#6370000
b1001011 1
b1001011 )
1$
#6380000
0$
#6390000
b1001100 )
b1001100 1
1$
#6400000
0$
#6410000
10
1(
b1001101 1
b1001101 )
1$
#6420000
0$
#6430000
0(
00
b11 -
b0 )
b100 4
b0 1
1$
#6440000
0$
#6450000
b1 1
b1 )
1$
#6460000
0$
#6470000
b10 )
b10 1
1$
#6480000
0$
#6490000
b11 1
b11 )
1$
#6500000
0$
#6510000
b100 )
b100 1
1$
#6520000
0$
#6530000
b101 1
b101 )
1$
#6540000
0$
#6550000
b110 )
b110 1
1$
#6560000
0$
#6570000
b111 1
b111 )
1$
#6580000
0$
#6590000
b1000 )
b1000 1
1$
#6600000
0$
#6610000
b1001 1
b1001 )
1$
#6620000
0$
#6630000
b1010 )
b1010 1
1$
#6640000
0$
#6650000
b1011 1
b1011 )
1$
#6660000
0$
#6670000
b1100 )
b1100 1
1$
#6680000
0$
#6690000
b1101 1
b1101 )
1$
#6700000
0$
#6710000
b1110 )
b1110 1
1$
#6720000
0$
#6730000
b1111 1
b1111 )
1$
#6740000
0$
#6750000
b10000 )
b10000 1
1$
#6760000
0$
#6770000
b10001 1
b10001 )
1$
#6780000
0$
#6790000
b10010 )
b10010 1
1$
#6800000
0$
#6810000
b10011 1
b10011 )
1$
#6820000
0$
#6830000
b10100 )
b10100 1
1$
#6840000
0$
#6850000
b10101 1
b10101 )
1$
#6860000
0$
#6870000
b10110 )
b10110 1
1$
#6880000
0$
#6890000
b10111 1
b10111 )
1$
#6900000
0$
#6910000
b11000 )
b11000 1
1$
#6920000
0$
#6930000
b11001 1
b11001 )
1$
#6940000
0$
#6950000
b11010 )
b11010 1
1$
#6960000
0$
#6970000
b11011 1
b11011 )
1$
#6980000
0$
#6990000
b11100 )
b11100 1
1$
#7000000
0$
#7010000
b11101 1
b11101 )
1$
#7020000
0$
#7030000
b11110 )
b11110 1
1$
#7040000
0$
#7050000
b11111 1
b11111 )
1$
#7060000
0$
#7070000
b100000 )
b100000 1
1$
#7080000
0$
#7090000
b100001 1
b100001 )
1$
#7100000
0$
#7110000
b100010 )
b100010 1
1$
#7120000
0$
#7130000
b100011 1
b100011 )
1$
#7140000
0$
#7150000
b100100 )
b100100 1
1$
#7160000
0$
#7170000
b100101 1
b100101 )
1$
#7180000
0$
#7190000
b100110 )
b100110 1
1$
#7200000
0$
#7210000
b100111 1
b100111 )
1$
#7220000
0$
#7230000
b101000 )
b101000 1
1$
#7240000
0$
#7250000
b101001 1
b101001 )
1$
#7260000
0$
#7270000
b101010 )
b101010 1
1$
#7280000
0$
#7290000
b101011 1
b101011 )
1$
#7300000
0$
#7310000
b101100 )
b101100 1
1$
#7320000
0$
#7330000
b101101 1
b101101 )
1$
#7340000
0$
#7350000
b101110 )
b101110 1
1$
#7360000
0$
#7370000
b101111 1
b101111 )
1$
#7380000
0$
#7390000
b110000 )
b110000 1
1$
#7400000
0$
#7410000
b110001 1
b110001 )
1$
#7420000
0$
#7430000
b110010 )
b110010 1
1$
#7440000
0$
#7450000
b110011 1
b110011 )
1$
#7460000
0$
#7470000
b110100 )
b110100 1
1$
#7480000
0$
#7490000
b110101 1
b110101 )
1$
#7500000
0$
#7510000
b110110 )
b110110 1
1$
#7520000
0$
#7530000
b110111 1
b110111 )
1$
#7540000
0$
#7550000
b111000 )
b111000 1
1$
#7560000
0$
#7570000
b111001 1
b111001 )
1$
#7580000
0$
#7590000
b111010 )
b111010 1
1$
#7600000
0$
#7610000
b111011 1
b111011 )
1$
#7620000
0$
#7630000
b111100 )
b111100 1
1$
#7640000
0$
#7650000
b111101 1
b111101 )
1$
#7660000
0$
#7670000
b111110 )
b111110 1
1$
#7680000
0$
#7690000
b111111 1
b111111 )
1$
#7700000
0$
#7710000
b1000000 )
b1000000 1
1$
#7720000
0$
#7730000
b1000001 1
b1000001 )
1$
#7740000
0$
#7750000
b1000010 )
b1000010 1
1$
#7760000
0$
#7770000
b1000011 1
b1000011 )
1$
#7780000
0$
#7790000
b1000100 )
b1000100 1
1$
#7800000
0$
#7810000
b1000101 1
b1000101 )
1$
#7820000
0$
#7830000
b1000110 )
b1000110 1
1$
#7840000
0$
#7850000
b1000111 1
b1000111 )
1$
#7860000
0$
#7870000
b1001000 )
b1001000 1
1$
#7880000
0$
#7890000
b1001001 1
b1001001 )
1$
#7900000
0$
#7910000
b1001010 )
b1001010 1
1$
#7920000
0$
#7930000
b1001011 1
b1001011 )
1$
#7940000
0$
#7950000
b1001100 )
b1001100 1
1$
#7960000
0$
#7970000
10
1(
b1001101 1
b1001101 )
1$
#7980000
0$
#7990000
0(
00
b100 -
b0 )
b101 4
b0 1
1$
#8000000
0$
#8010000
b1 1
b1 )
1$
#8020000
0$
#8030000
b10 )
b10 1
1$
#8040000
0$
#8050000
b11 1
b11 )
1$
#8060000
0$
#8070000
b100 )
b100 1
1$
#8080000
0$
#8090000
b101 1
b101 )
1$
#8100000
0$
#8110000
b110 )
b110 1
1$
#8120000
0$
#8130000
b111 1
b111 )
1$
#8140000
0$
#8150000
b1000 )
b1000 1
1$
#8160000
0$
#8170000
b1001 1
b1001 )
1$
#8180000
0$
#8190000
b1010 )
b1010 1
1$
#8200000
0$
#8210000
b1011 1
b1011 )
1$
#8220000
0$
#8230000
b1100 )
b1100 1
1$
#8240000
0$
#8250000
b1101 1
b1101 )
1$
#8260000
0$
#8270000
b1110 )
b1110 1
1$
#8280000
0$
#8290000
b1111 1
b1111 )
1$
#8300000
0$
