5-lifNeuron/lifNeuron.sv
module lifNeuron (
    input logic clk,
    input logic resetn,

    input logic [5:0] inWeight,

    output logic outSpike
);

  localparam logic [5:0] THRESHOLD = 6'd10;

  logic [5:0] membranePotential;

  logic nextSpike;
  logic [5:0] nextPotential;

  always_comb begin
    nextPotential = membranePotential;
    nextSpike = 1'b0;

    //integrate
    if (inWeight > 0) begin
      if (membranePotential > (6'd63 - inWeight)) begin
        nextPotential = 6'd63;
      end else begin
        nextPotential = membranePotential + inWeight;
      end
    end

    //leak
    if (nextPotential > 6'd0) begin
      nextPotential = nextPotential - 6'd1;
    end

    //fire
    if (nextPotential >= THRESHOLD) begin
      nextSpike = 1'b1;
      nextPotential = 6'd0;
    end
  end

  always_ff @(posedge clk) begin
    if (!resetn) begin
      outSpike <= 1'b0;
      membranePotential <= 6'd0;
    end else begin
      outSpike <= nextSpike;
      membranePotential <= nextPotential;
    end
  end

endmodule

5-lifNeuron/lifSynapse.sv
module lifSynapse (
    input logic inSpike,
    output logic [5:0] weight
);

  logic [5:0] currentWeight;

  initial begin
    currentWeight = 6'd7;
  end

  always_comb begin
    if (inSpike) begin
      weight = currentWeight;
    end else weight = 6'd0;
  end

endmodule

5-lifNeuron/lifNetwork.sv
module lifNetwork (
    input  logic clk,
    input  logic resetn,
    input  logic inSpike,
    output logic outSpike
);

  logic [5:0] neuron1Weight;
  logic neuron1Out;
  logic [5:0] neuron2Weight;
  logic neuron2Out;
  logic [5:0] neuron3Weight;
  logic neuron3Out;
  logic [5:0] neuron4Weight1;
  logic [5:0] neuron4Weight2;

  lifSynapse synapse1 (
      .inSpike(inSpike),
      .weight (neuron1Weight)
  );

  lifNeuron neuron1 (
      .clk(clk),
      .resetn(resetn),
      .inWeight(neuron1Weight),
      .outSpike(neuron1Out)
  );

  lifSynapse synapse2 (
      .inSpike(neuron1Out),
      .weight (neuron2Weight)
  );

  lifSynapse synapse3 (
      .inSpike(neuron1Out),
      .weight (neuron3Weight)
  );

  lifNeuron neuron2 (
      .clk(clk),
      .resetn(resetn),
      .inWeight(neuron2Weight),
      .outSpike(neuron2Out)
  );

  lifNeuron neuron3 (
      .clk(clk),
      .resetn(resetn),
      .inWeight(neuron3Weight),
      .outSpike(neuron3Out)
  );

  lifSynapse synapse4 (
      .inSpike(neuron2Out),
      .weight (neuron4Weight1)
  );

  lifSynapse synapse5 (
      .inSpike(neuron3Out),
      .weight (neuron4Weight2)
  );

  lifNeuron neuron4 (
      .clk(clk),
      .resetn(resetn),
      .inWeight(neuron4Weight1 + neuron4Weight2),
      .outSpike(outSpike)
  );


endmodule

5-lifNeuron/tb_lifNetwork.sv
`timescale 1ns / 1ps

module tb_lifNetwork ();

  logic clk;
  logic resetn;
  logic inSpike;
  logic outSpike;

  lifNetwork uut (
      .clk(clk),
      .resetn(resetn),
      .inSpike(inSpike),
      .outSpike(outSpike)
  );

  // 100 MHz clock
  initial begin
    clk = 0;
    forever #5 clk = ~clk;
  end

  // Dump waveforms for GTKWave
  initial begin
    $dumpfile("lifNetwork.vcd");
    $dumpvars(0, tb_lifNetwork);
  end

  initial begin

    // Initial values
    resetn  = 0;
    inSpike = 0;

    // Hold reset for a few clocks
    repeat (3) @(posedge clk);
    resetn = 1;

    // -------------------------
    // Single spike
    // -------------------------
    @(posedge clk);
    inSpike = 1;

    @(posedge clk);
    inSpike = 0;

    // Wait for leak
    repeat (10) @(posedge clk);

    // -------------------------
    // Burst of spikes
    // -------------------------
    repeat (10) begin
      @(posedge clk);
      inSpike = 1;

      @(posedge clk);
      inSpike = 0;
    end

    // Allow activity to propagate
    repeat (20) @(posedge clk);

    $finish;
  end

endmodule

5-lifNeuron/lifNetwork.vcd
$date
	Wed Jul  8 21:16:49 2026
$end
$version
	Icarus Verilog
$end
$timescale
	1ps
$end
$scope module tb_lifNetwork $end
$var wire 1 ! outSpike $end
$var reg 1 " clk $end
$var reg 1 # inSpike $end
$var reg 1 $ resetn $end
$scope module uut $end
$var wire 1 " clk $end
$var wire 1 # inSpike $end
$var wire 1 $ resetn $end
$var wire 1 ! outSpike $end
$var wire 6 % neuron4Weight2 [5:0] $end
$var wire 6 & neuron4Weight1 [5:0] $end
$var wire 6 ' neuron3Weight [5:0] $end
$var wire 1 ( neuron3Out $end
$var wire 6 ) neuron2Weight [5:0] $end
$var wire 1 * neuron2Out $end
$var wire 6 + neuron1Weight [5:0] $end
$var wire 1 , neuron1Out $end
$scope module neuron1 $end
$var wire 1 " clk $end
$var wire 1 $ resetn $end
$var wire 6 - inWeight [5:0] $end
$var parameter 6 . THRESHOLD $end
$var reg 6 / membranePotential [5:0] $end
$var reg 6 0 nextPotential [5:0] $end
$var reg 1 1 nextSpike $end
$var reg 1 , outSpike $end
$upscope $end
$scope module neuron2 $end
$var wire 1 " clk $end
$var wire 1 $ resetn $end
$var wire 6 2 inWeight [5:0] $end
$var parameter 6 3 THRESHOLD $end
$var reg 6 4 membranePotential [5:0] $end
$var reg 6 5 nextPotential [5:0] $end
$var reg 1 6 nextSpike $end
$var reg 1 * outSpike $end
$upscope $end
$scope module neuron3 $end
$var wire 1 " clk $end
$var wire 1 $ resetn $end
$var wire 6 7 inWeight [5:0] $end
$var parameter 6 8 THRESHOLD $end
$var reg 6 9 membranePotential [5:0] $end
$var reg 6 : nextPotential [5:0] $end
$var reg 1 ; nextSpike $end
$var reg 1 ( outSpike $end
$upscope $end
$scope module neuron4 $end
$var wire 1 " clk $end
$var wire 6 < inWeight [5:0] $end
$var wire 1 $ resetn $end
$var parameter 6 = THRESHOLD $end
$var reg 6 > membranePotential [5:0] $end
$var reg 6 ? nextPotential [5:0] $end
$var reg 1 @ nextSpike $end
$var reg 1 ! outSpike $end
$upscope $end
$scope module synapse1 $end
$var wire 1 # inSpike $end
$var reg 6 A currentWeight [5:0] $end
$var reg 6 B weight [5:0] $end
$upscope $end
$scope module synapse2 $end
$var wire 1 , inSpike $end
$var reg 6 C currentWeight [5:0] $end
$var reg 6 D weight [5:0] $end
$upscope $end
$scope module synapse3 $end
$var wire 1 , inSpike $end
$var reg 6 E currentWeight [5:0] $end
$var reg 6 F weight [5:0] $end
$upscope $end
$scope module synapse4 $end
$var wire 1 * inSpike $end
$var reg 6 G currentWeight [5:0] $end
$var reg 6 H weight [5:0] $end
$upscope $end
$scope module synapse5 $end
$var wire 1 ( inSpike $end
$var reg 6 I currentWeight [5:0] $end
$var reg 6 J weight [5:0] $end
$upscope $end
$upscope $end
$upscope $end
$enddefinitions $end
$comment Show the parameter values. $end
$dumpall
b1010 =
b1010 8
b1010 3
b1010 .
$end
#0
$dumpvars
b0 J
b111 I
b0 H
b111 G
b0 F
b111 E
b0 D
b111 C
b0 B
b111 A
0@
bx ?
bx >
b0 <
0;
bx :
bx 9
b0 7
06
bx 5
bx 4
b0 2
01
bx 0
bx /
b0 -
x,
b0 +
x*
b0 )
x(
b0 '
b0 &
b0 %
0$
0#
0"
x!
$end
#5000
b0 0
b0 5
b0 :
b0 ?
b0 /
0,
b0 4
0*
b0 9
0(
b0 >
0!
1"
#10000
0"
#15000
1"
#20000
0"
#25000
1$
1"
#30000
0"
#35000
b110 0
b111 +
b111 -
b111 B
1#
1"
#40000
0"
#45000
b110 /
b101 0
b0 +
b0 -
b0 B
0#
1"
#50000
0"
#55000
b100 0
b101 /
1"
#60000
0"
#65000
b11 0
b100 /
1"
#70000
0"
#75000
b10 0
b11 /
1"
#80000
0"
#85000
b1 0
b10 /
1"
#90000
0"
#95000
b0 0
b1 /
1"
#100000
0"
#105000
b0 /
1"
#110000
0"
#115000
1"
#120000
0"
#125000
1"
#130000
0"
#135000
1"
#140000
0"
#145000
1"
#150000
0"
#155000
b110 0
b111 +
b111 -
b111 B
1#
1"
#160000
0"
#165000
b110 /
b101 0
b0 +
b0 -
b0 B
0#
1"
#170000
0"
#175000
b101 /
11
b0 0
b111 +
b111 -
b111 B
1#
1"
#180000
0"
#185000
b110 5
b110 :
b111 )
b111 2
b111 D
b111 '
b111 7
b111 F
b0 /
1,
01
b0 0
b0 +
b0 -
b0 B
0#
1"
#190000
0"
#195000
b101 :
b101 5
b0 )
b0 2
b0 D
b0 '
b0 7
b0 F
b110 9
b110 4
0,
b110 0
b111 +
b111 -
b111 B
1#
1"
#200000
0"
#205000
b100 5
b100 :
b110 /
b101 4
b101 9
b101 0
b0 +
b0 -
b0 B
0#
1"
#210000
0"
#215000
b11 :
b11 5
b100 9
b100 4
b101 /
11
b0 0
b111 +
b111 -
b111 B
1#
1"
#220000
0"
#225000
b111 )
b111 2
b111 D
b111 '
b111 7
b111 F
b1001 5
b1001 :
b0 /
1,
b11 4
b11 9
01
b0 0
b0 +
b0 -
b0 B
0#
1"
#230000
0"
#235000
b1000 :
b1000 5
b0 )
b0 2
b0 D
b0 '
b0 7
b0 F
b1001 9
b1001 4
0,
b110 0
b111 +
b111 -
b111 B
1#
1"
#240000
0"
#245000
b111 5
b111 :
b110 /
b1000 4
b1000 9
b101 0
b0 +
b0 -
b0 B
0#
1"
#250000
0"
#255000
b110 :
b110 5
b111 9
b111 4
b101 /
11
b0 0
b111 +
b111 -
b111 B
1#
1"
#260000
0"
#265000
16
1;
b111 )
b111 2
b111 D
b111 '
b111 7
b111 F
b0 5
b0 :
b0 /
1,
b110 4
b110 9
01
b0 0
b0 +
b0 -
b0 B
0#
1"
#270000
0"
#275000
1@
b0 ?
0;
b111 %
b111 J
06
b1110 <
b111 &
b111 H
b0 )
b0 2
b0 D
b0 '
b0 7
b0 F
b0 9
1(
b0 4
1*
0,
b110 0
b111 +
b111 -
b111 B
1#
1"
#280000
0"
#285000
0@
b0 &
b0 H
b0 <
b0 %
b0 J
b110 /
0*
0(
1!
b101 0
b0 +
b0 -
b0 B
0#
1"
#290000
0"
#295000
0!
b101 /
11
b0 0
b111 +
b111 -
b111 B
1#
1"
#300000
0"
#305000
b110 5
b110 :
b111 )
b111 2
b111 D
b111 '
b111 7
b111 F
b0 /
1,
01
b0 0
b0 +
b0 -
b0 B
0#
1"
#310000
0"
#315000
b101 :
b101 5
b0 )
b0 2
b0 D
b0 '
b0 7
b0 F
b110 9
b110 4
0,
b110 0
b111 +
b111 -
b111 B
1#
1"
#320000
0"
#325000
b100 5
b100 :
b110 /
b101 4
b101 9
b101 0
b0 +
b0 -
b0 B
0#
1"
#330000
0"
#335000
b11 :
b11 5
b100 9
b100 4
b101 /
11
b0 0
b111 +
b111 -
b111 B
1#
1"
#340000
0"
#345000
b111 )
b111 2
b111 D
b111 '
b111 7
b111 F
b1001 5
b1001 :
b0 /
1,
b11 4
b11 9
01
b0 0
b0 +
b0 -
b0 B
0#
1"
#350000
0"
#355000
b1000 :
b1000 5
b0 )
b0 2
b0 D
b0 '
b0 7
b0 F
b1001 9
b1001 4
0,
1"
#360000
0"
#365000
b111 5
b111 :
b1000 4
b1000 9
1"
#370000
0"
#375000
b110 :
b110 5
b111 9
b111 4
1"
#380000
0"
#385000
b101 5
b101 :
b110 4
b110 9
1"
#390000
0"
#395000
b100 :
b100 5
b101 9
b101 4
1"
#400000
0"
#405000
b11 5
b11 :
b100 4
b100 9
1"
#410000
0"
#415000
b10 :
b10 5
b11 9
b11 4
1"
#420000
0"
#425000
b1 5
b1 :
b10 4
b10 9
1"
#430000
0"
#435000
b0 :
b0 5
b1 9
b1 4
1"
#440000
0"
#445000
b0 4
b0 9
1"
