5-lifNeuron/lifNeuron.sv
module lifNeuron (
    input logic clk,
    input logic resetn,

    input logic inSpike,

    output logic outSpike
);

  localparam logic [5:0] WEIGHT = 6'd4;
  localparam logic [5:0] THRESHOLD = 6'd10;

  logic [5:0] membranePotential;

  logic nextSpike;
  logic [5:0] nextPotential;

  always_comb begin
    nextPotential = membranePotential;
    nextSpike = 1'b0;

    //integrate
    if (inSpike) begin
      if (membranePotential > (6'd63 - WEIGHT)) begin
        nextPotential = 6'd63;
      end else begin
        nextPotential = membranePotential + WEIGHT;
      end
    end

    //leak
    if (nextPotential > 6'd0) begin
      nextPotential = nextPotential - 6'd1;
    end

    //fire
    if (nextPotential >= THRESHOLD) begin
      nextSpike = 1'b1;
      nextPotential = 6'd0;
    end
  end

  always_ff @(posedge clk) begin
    if (!resetn) begin
      outSpike <= 1'b0;
      membranePotential <= 6'd0;
    end else begin
      outSpike <= nextSpike;
      membranePotential <= nextPotential;
    end
  end

endmodule

5-lifNeuron/lifNeuron_tb.sv
`timescale 1ns / 1ps

module lifNeuron_tb;

  logic clk;
  logic resetn;
  logic inSpike;
  logic outSpike;


  lifNeuron uut (
      .clk(clk),
      .resetn(resetn),
      .inSpike(inSpike),
      .outSpike(outSpike)
  );

  initial begin
    clk = 0;
    forever begin
      #5 clk = ~clk;
    end
  end


  initial begin
    $dumpfile("lifNueron_sim.vcd");
    $dumpvars(0, lifNeuron_tb);

    resetn  = 0;
    inSpike = 0;

    #15;
    resetn = 1;

    #10;
    inSpike = 1;
    #10;
    inSpike = 0;

    #10;
    inSpike = 1;
    #10;
    inSpike = 0;

    #10;
    inSpike = 1;
    #10;
    inSpike = 0;

    #50;

    $display("Simulation Finished!");
    $finish;
  end

endmodule

5-lifNeuron/lifNueron_sim.vcd
$date
	Mon Jul  6 12:51:59 2026
$end
$version
	Icarus Verilog
$end
$timescale
	1ps
$end
$scope module lifNeuron_tb $end
$var wire 1 ! outSpike $end
$var reg 1 " clk $end
$var reg 1 # inSpike $end
$var reg 1 $ resetn $end
$scope module uut $end
$var wire 1 " clk $end
$var wire 1 # inSpike $end
$var wire 1 $ resetn $end
$var parameter 6 % THRESHOLD $end
$var parameter 6 & WEIGHT $end
$var reg 6 ' membranePotential [5:0] $end
$var reg 6 ( nextPotential [5:0] $end
$var reg 1 ) nextSpike $end
$var reg 1 ! outSpike $end
$upscope $end
$upscope $end
$enddefinitions $end
$comment Show the parameter values. $end
$dumpall
b100 &
b1010 %
$end
#0
$dumpvars
0)
bx (
bx '
0$
0#
0"
x!
$end
#5000
b0 (
b0 '
0!
1"
#10000
0"
#15000
1"
1$
#20000
0"
#25000
b11 '
b110 (
1"
1#
#30000
0"
#35000
b10 '
b1 (
1"
0#
#40000
0"
#45000
b101 '
b1000 (
1"
1#
#50000
0"
#55000
b100 '
b11 (
1"
0#
#60000
0"
#65000
1)
b111 '
b0 (
1"
1#
#70000
0"
#75000
b110 '
0)
b101 (
1"
0#
#80000
0"
#85000
b100 (
b101 '
1"
#90000
0"
#95000
b11 (
b100 '
1"
#100000
0"
#105000
b10 (
b11 '
1"
#110000
0"
#115000
b1 (
b10 '
1"
#120000
0"
#125000
b0 (
b1 '
1"
