5-lifNeuron/ledPulseStretcher.sv
module ledPulseStretcher #(
    parameter int COUNT_MAX = 10_000_000
) (
    input  logic clk,
    input  logic resetn,
    input  logic spike,
    output logic led
);

  logic [31:0] counter;

  always_ff @(posedge clk) begin
    if (!resetn) begin
      counter <= '0;
      led <= 1'b1;
    end else begin
      if (spike) begin
        counter <= COUNT_MAX - 1;
        led <= 1'b0;
      end else if (counter != 0) begin
        counter <= counter - 1'b1;
        led <= 1'b0;
      end else begin
        led <= 1'b1;
      end
    end
  end

endmodule

5-lifNeuron/lifSynapse.sv
module lifSynapse #(
    parameter int DATA_WIDTH = 6,
    parameter logic [DATA_WIDTH-1:0] WEIGHT = 7,
    parameter logic [DATA_WIDTH-1:0] RESET_WEIGHT = 0
) (
    input logic inSpike,
    output logic [DATA_WIDTH-1:0] weight
);

  always_comb begin
    if (inSpike) begin
      weight = WEIGHT;
    end else weight = RESET_WEIGHT;
  end

endmodule

5-lifNeuron/lifNeuron.sv
module lifNeuron #(
    parameter int DATA_WIDTH = 6,
    parameter logic [DATA_WIDTH-1:0] THRESHOLD = 'd10,
    parameter logic [DATA_WIDTH-1:0] LEAK = 'd1,
    parameter logic [DATA_WIDTH-1:0] RESET_POTENTIAL = '0

) (
    input logic clk,
    input logic resetn,

    input logic [DATA_WIDTH-1:0] inWeight,

    output logic outSpike
);

  logic [DATA_WIDTH-1:0] membranePotential;

  logic nextSpike;
  logic [DATA_WIDTH-1:0] nextPotential;

  always_comb begin
    nextPotential = membranePotential;
    nextSpike = 1'b0;

    //integrate
    if (inWeight > 0) begin
      if (membranePotential > (((2 ** DATA_WIDTH) - 1) - inWeight)) begin
        nextPotential = (2 ** DATA_WIDTH) - 1;
      end else begin
        nextPotential = membranePotential + inWeight;
      end
    end  //leak
    else if (nextPotential > '0) begin
      nextPotential = nextPotential - LEAK;
    end

    //fire
    if (nextPotential >= THRESHOLD) begin
      nextSpike = 1'b1;
      nextPotential = RESET_POTENTIAL;
    end
  end

  always_ff @(posedge clk) begin
    if (!resetn) begin
      outSpike <= 1'b0;
      membranePotential <= '0;
    end else begin
      outSpike <= nextSpike;
      membranePotential <= nextPotential;
    end
  end

endmodule

5-lifNeuron/lifNetwork.sv
module lifNetwork #(
    parameter int NUM_NEURONS = 64,
    parameter int DATA_WIDTH  = 6
) (
    input logic clk,
    input logic resetn,
    input logic [NUM_NEURONS-1:0] inSpike,
    output logic [NUM_NEURONS-1:0] outSpike
);

  localparam int SUMWIDTH = DATA_WIDTH + $clog2(NUM_NEURONS);

  logic [NUM_NEURONS-1:0] networkSpikes;
  logic [DATA_WIDTH-1:0] contributions[NUM_NEURONS][NUM_NEURONS];
  logic [SUMWIDTH-1:0] synapticWeights[NUM_NEURONS];

  genvar i;
  genvar j;

  generate
    for (i = 0; i < NUM_NEURONS; i++) begin : gen_neurons
      lifNeuron #(
          .DATA_WIDTH(SUMWIDTH),
          .THRESHOLD(16),
          .LEAK(1),
          .RESET_POTENTIAL(0)
      ) neuron (
          .clk(clk),
          .resetn(resetn),
          .inWeight(synapticWeights[i]),
          .outSpike(networkSpikes[i])
      );
      for (j = 0; j < NUM_NEURONS; j++) begin : gen_synapses
        lifSynapse #(
            .DATA_WIDTH(DATA_WIDTH),
            .WEIGHT(32),
            .RESET_WEIGHT(0)
        ) synapse (
            .inSpike(networkSpikes[j] | inSpike[j]),
            .weight (contributions[i][j])
        );
      end
    end
  endgenerate

  always_comb begin
    for (int k = 0; k < NUM_NEURONS; k++) begin
      synapticWeights[k] = '0;
      for (int l = 0; l < NUM_NEURONS; l++) begin
        synapticWeights[k] = synapticWeights[k] + SUMWIDTH'(contributions[k][l]);
      end
    end
  end

  assign outSpike = networkSpikes;

endmodule

5-lifNeuron/debouncer.sv
module debouncer #(
    parameter int COUNT_MAX = 2_500_000  // e.g., 25ms window at a 100MHz clock
) (
    input  logic clk,
    input  logic resetn,
    input  logic button_in,
    output logic button_out
);

  logic btn_sync_0;
  logic btn_sync_1;
  logic [31:0] counter;

  always_ff @(posedge clk) begin
    if (!resetn) begin
      btn_sync_0 <= 1'b1;
      btn_sync_1 <= 1'b1;
    end else begin
      btn_sync_0 <= button_in;
      btn_sync_1 <= btn_sync_0;
    end
  end

  always_ff @(posedge clk) begin
    if (!resetn) begin
      button_out <= 1'b1;
      counter    <= '0;
    end else begin
      if (btn_sync_1 != button_out) begin
        if (counter < COUNT_MAX - 1) begin
          counter <= counter + 1'b1;
        end else begin
          button_out <= btn_sync_1;
          counter    <= '0;
        end
      end else begin
        counter <= '0;
      end
    end
  end

endmodule

5-lifNeuron/top.sv
module top (
    input logic clk,
    input logic resetn,
    input logic button,
    output logic [3:0] led
);

  logic [3:0] spikes;
  logic [3:0] neuronSpikes;

  logic previous_button;
  logic button_pressed;
  logic button_db;

  debouncer #(
      .COUNT_MAX(2_500_000)
  ) debounce (
      .clk(clk),
      .resetn(resetn),
      .button_in(button),
      .button_out(button_db)
  );

  always_ff @(posedge clk) begin
    if (!resetn) begin
      previous_button <= 1'b1;
      button_pressed  <= 1'b0;
    end else begin
      previous_button <= button_db;
      button_pressed  <= previous_button && !button_db;
    end
  end

  assign spikes[0] = button_pressed;
  assign spikes[1] = 1'b0;
  assign spikes[2] = 1'b0;
  assign spikes[3] = 1'b0;

  lifNetwork #(
      .NUM_NEURONS(4),
      .DATA_WIDTH (6)
  ) network (
      .clk(clk),
      .resetn(resetn),
      .inSpike(spikes),
      .outSpike(neuronSpikes)
  );

  ledPulseStretcher #(
      .COUNT_MAX(10_000_000)
  ) led0 (
      .clk(clk),
      .resetn(resetn),
      .spike(neuronSpikes[0]),
      .led(led[0])
  );

  ledPulseStretcher #(
      .COUNT_MAX(10_000_000)
  ) led1 (
      .clk(clk),
      .resetn(resetn),
      .spike(neuronSpikes[1]),
      .led(led[1])
  );

  ledPulseStretcher #(
      .COUNT_MAX(10_000_000)
  ) led2 (
      .clk(clk),
      .resetn(resetn),
      .spike(neuronSpikes[2]),
      .led(led[2])
  );

  ledPulseStretcher #(
      .COUNT_MAX(10_000_000)
  ) led3 (
      .clk(clk),
      .resetn(resetn),
      .spike(neuronSpikes[3]),
      .led(led[3])
  );

endmodule

5-lifNeuron/tb_top.sv
`timescale 1ns / 1ps

module tb_top;

  logic clk;
  logic resetn;
  logic button;
  logic [3:0] led;

  top dut (
      .clk(clk),
      .resetn(resetn),
      .button(button),
      .led(led)
  );

  initial clk = 0;
  always #5 clk = ~clk;


  initial begin
    $dumpfile("top.vcd");
    $dumpvars(0, tb_top);

    // Initialize inputs
    resetn = 0;
    button = 1;  // Idle state for active-low is High

    // Hold reset for a few cycles
    repeat (5) @(posedge clk);
    resetn = 1;
    repeat (5) @(posedge clk);

    // --- TEST ACTION: Clean Button Press ---
    $display("Pressing button...");
    button = 0;  // Press (Active-Low)

    // Hold it down for 10 cycles (longer than COUNT_MAX = 5)
    repeat (10) @(posedge clk);

    $display("Releasing button...");
    button = 1;  // Release

    // Wait long enough to see the network process and the LED stretch
    repeat (50) @(posedge clk);

    $finish;
  end

endmodule

5-lifNeuron/top.vcd
$version Generated by VerilatedVcd $end
$timescale 1ps $end
 $scope module tb_top $end
  $var wire 1 ` clk $end
  $var wire 1 a resetn $end
  $var wire 1 b button $end
  $var wire 4 " led [3:0] $end
  $scope module dut $end
   $var wire 1 ` clk $end
   $var wire 1 a resetn $end
   $var wire 1 b button $end
   $var wire 4 " led [3:0] $end
   $var wire 4 # spikes [3:0] $end
   $var wire 4 $ neuronSpikes [3:0] $end
   $var wire 1 % previous_button $end
   $var wire 1 & button_pressed $end
   $var wire 1 ' button_db $end
   $scope module debounce $end
    $var wire 32 c COUNT_MAX [31:0] $end
    $var wire 1 ` clk $end
    $var wire 1 a resetn $end
    $var wire 1 b button_in $end
    $var wire 1 ' button_out $end
    $var wire 1 ( btn_sync_0 $end
    $var wire 1 ) btn_sync_1 $end
    $var wire 32 * counter [31:0] $end
   $upscope $end
   $scope module led0 $end
    $var wire 32 d COUNT_MAX [31:0] $end
    $var wire 1 ` clk $end
    $var wire 1 a resetn $end
    $var wire 1 + spike $end
    $var wire 1 , led $end
    $var wire 32 - counter [31:0] $end
   $upscope $end
   $scope module led1 $end
    $var wire 32 d COUNT_MAX [31:0] $end
    $var wire 1 ` clk $end
    $var wire 1 a resetn $end
    $var wire 1 . spike $end
    $var wire 1 / led $end
    $var wire 32 0 counter [31:0] $end
   $upscope $end
   $scope module led2 $end
    $var wire 32 d COUNT_MAX [31:0] $end
    $var wire 1 ` clk $end
    $var wire 1 a resetn $end
    $var wire 1 1 spike $end
    $var wire 1 2 led $end
    $var wire 32 3 counter [31:0] $end
   $upscope $end
   $scope module led3 $end
    $var wire 32 d COUNT_MAX [31:0] $end
    $var wire 1 ` clk $end
    $var wire 1 a resetn $end
    $var wire 1 4 spike $end
    $var wire 1 5 led $end
    $var wire 32 6 counter [31:0] $end
   $upscope $end
   $scope module network $end
    $var wire 32 e NUM_NEURONS [31:0] $end
    $var wire 32 f DATA_WIDTH [31:0] $end
    $var wire 1 ` clk $end
    $var wire 1 a resetn $end
    $var wire 4 # inSpike [3:0] $end
    $var wire 4 $ outSpike [3:0] $end
    $var wire 32 g SUMWIDTH [31:0] $end
    $var wire 4 $ networkSpikes [3:0] $end
    $var wire 6 7 contributions[0][0] [5:0] $end
    $var wire 6 8 contributions[0][1] [5:0] $end
    $var wire 6 9 contributions[0][2] [5:0] $end
    $var wire 6 : contributions[0][3] [5:0] $end
    $var wire 6 ; contributions[1][0] [5:0] $end
    $var wire 6 < contributions[1][1] [5:0] $end
    $var wire 6 = contributions[1][2] [5:0] $end
    $var wire 6 > contributions[1][3] [5:0] $end
    $var wire 6 ? contributions[2][0] [5:0] $end
    $var wire 6 @ contributions[2][1] [5:0] $end
    $var wire 6 A contributions[2][2] [5:0] $end
    $var wire 6 B contributions[2][3] [5:0] $end
    $var wire 6 C contributions[3][0] [5:0] $end
    $var wire 6 D contributions[3][1] [5:0] $end
    $var wire 6 E contributions[3][2] [5:0] $end
    $var wire 6 F contributions[3][3] [5:0] $end
    $var wire 8 G synapticWeights[0] [7:0] $end
    $var wire 8 H synapticWeights[1] [7:0] $end
    $var wire 8 I synapticWeights[2] [7:0] $end
    $var wire 8 J synapticWeights[3] [7:0] $end
    $scope module gen_neurons[0] $end
     $scope module gen_synapses[0] $end
      $scope module synapse $end
       $var wire 32 f DATA_WIDTH [31:0] $end
       $var wire 6 h WEIGHT [5:0] $end
       $var wire 6 i RESET_WEIGHT [5:0] $end
       $var wire 1 K inSpike $end
       $var wire 6 L weight [5:0] $end
      $upscope $end
     $upscope $end
     $scope module gen_synapses[1] $end
      $scope module synapse $end
       $var wire 32 f DATA_WIDTH [31:0] $end
       $var wire 6 h WEIGHT [5:0] $end
       $var wire 6 i RESET_WEIGHT [5:0] $end
       $var wire 1 . inSpike $end
       $var wire 6 M weight [5:0] $end
      $upscope $end
     $upscope $end
     $scope module gen_synapses[2] $end
      $scope module synapse $end
       $var wire 32 f DATA_WIDTH [31:0] $end
       $var wire 6 h WEIGHT [5:0] $end
       $var wire 6 i RESET_WEIGHT [5:0] $end
       $var wire 1 1 inSpike $end
       $var wire 6 N weight [5:0] $end
      $upscope $end
     $upscope $end
     $scope module gen_synapses[3] $end
      $scope module synapse $end
       $var wire 32 f DATA_WIDTH [31:0] $end
       $var wire 6 h WEIGHT [5:0] $end
       $var wire 6 i RESET_WEIGHT [5:0] $end
       $var wire 1 4 inSpike $end
       $var wire 6 O weight [5:0] $end
      $upscope $end
     $upscope $end
     $scope module neuron $end
      $var wire 32 g DATA_WIDTH [31:0] $end
      $var wire 8 j THRESHOLD [7:0] $end
      $var wire 8 k LEAK [7:0] $end
      $var wire 8 l RESET_POTENTIAL [7:0] $end
      $var wire 1 ` clk $end
      $var wire 1 a resetn $end
      $var wire 8 P inWeight [7:0] $end
      $var wire 1 + outSpike $end
      $var wire 8 Q membranePotential [7:0] $end
      $var wire 1 R nextSpike $end
      $var wire 8 S nextPotential [7:0] $end
     $upscope $end
    $upscope $end
    $scope module gen_neurons[1] $end
     $scope module gen_synapses[0] $end
      $scope module synapse $end
       $var wire 32 f DATA_WIDTH [31:0] $end
       $var wire 6 h WEIGHT [5:0] $end
       $var wire 6 i RESET_WEIGHT [5:0] $end
       $var wire 1 K inSpike $end
       $var wire 6 L weight [5:0] $end
      $upscope $end
     $upscope $end
     $scope module gen_synapses[1] $end
      $scope module synapse $end
       $var wire 32 f DATA_WIDTH [31:0] $end
       $var wire 6 h WEIGHT [5:0] $end
       $var wire 6 i RESET_WEIGHT [5:0] $end
       $var wire 1 . inSpike $end
       $var wire 6 M weight [5:0] $end
      $upscope $end
     $upscope $end
     $scope module gen_synapses[2] $end
      $scope module synapse $end
       $var wire 32 f DATA_WIDTH [31:0] $end
       $var wire 6 h WEIGHT [5:0] $end
       $var wire 6 i RESET_WEIGHT [5:0] $end
       $var wire 1 1 inSpike $end
       $var wire 6 N weight [5:0] $end
      $upscope $end
     $upscope $end
     $scope module gen_synapses[3] $end
      $scope module synapse $end
       $var wire 32 f DATA_WIDTH [31:0] $end
       $var wire 6 h WEIGHT [5:0] $end
       $var wire 6 i RESET_WEIGHT [5:0] $end
       $var wire 1 4 inSpike $end
       $var wire 6 O weight [5:0] $end
      $upscope $end
     $upscope $end
     $scope module neuron $end
      $var wire 32 g DATA_WIDTH [31:0] $end
      $var wire 8 j THRESHOLD [7:0] $end
      $var wire 8 k LEAK [7:0] $end
      $var wire 8 l RESET_POTENTIAL [7:0] $end
      $var wire 1 ` clk $end
      $var wire 1 a resetn $end
      $var wire 8 T inWeight [7:0] $end
      $var wire 1 . outSpike $end
      $var wire 8 U membranePotential [7:0] $end
      $var wire 1 V nextSpike $end
      $var wire 8 W nextPotential [7:0] $end
     $upscope $end
    $upscope $end
    $scope module gen_neurons[2] $end
     $scope module gen_synapses[0] $end
      $scope module synapse $end
       $var wire 32 f DATA_WIDTH [31:0] $end
       $var wire 6 h WEIGHT [5:0] $end
       $var wire 6 i RESET_WEIGHT [5:0] $end
       $var wire 1 K inSpike $end
       $var wire 6 L weight [5:0] $end
      $upscope $end
     $upscope $end
     $scope module gen_synapses[1] $end
      $scope module synapse $end
       $var wire 32 f DATA_WIDTH [31:0] $end
       $var wire 6 h WEIGHT [5:0] $end
       $var wire 6 i RESET_WEIGHT [5:0] $end
       $var wire 1 . inSpike $end
       $var wire 6 M weight [5:0] $end
      $upscope $end
     $upscope $end
     $scope module gen_synapses[2] $end
      $scope module synapse $end
       $var wire 32 f DATA_WIDTH [31:0] $end
       $var wire 6 h WEIGHT [5:0] $end
       $var wire 6 i RESET_WEIGHT [5:0] $end
       $var wire 1 1 inSpike $end
       $var wire 6 N weight [5:0] $end
      $upscope $end
     $upscope $end
     $scope module gen_synapses[3] $end
      $scope module synapse $end
       $var wire 32 f DATA_WIDTH [31:0] $end
       $var wire 6 h WEIGHT [5:0] $end
       $var wire 6 i RESET_WEIGHT [5:0] $end
       $var wire 1 4 inSpike $end
       $var wire 6 O weight [5:0] $end
      $upscope $end
     $upscope $end
     $scope module neuron $end
      $var wire 32 g DATA_WIDTH [31:0] $end
      $var wire 8 j THRESHOLD [7:0] $end
      $var wire 8 k LEAK [7:0] $end
      $var wire 8 l RESET_POTENTIAL [7:0] $end
      $var wire 1 ` clk $end
      $var wire 1 a resetn $end
      $var wire 8 X inWeight [7:0] $end
      $var wire 1 1 outSpike $end
      $var wire 8 Y membranePotential [7:0] $end
      $var wire 1 Z nextSpike $end
      $var wire 8 [ nextPotential [7:0] $end
     $upscope $end
    $upscope $end
    $scope module gen_neurons[3] $end
     $scope module gen_synapses[0] $end
      $scope module synapse $end
       $var wire 32 f DATA_WIDTH [31:0] $end
       $var wire 6 h WEIGHT [5:0] $end
       $var wire 6 i RESET_WEIGHT [5:0] $end
       $var wire 1 K inSpike $end
       $var wire 6 L weight [5:0] $end
      $upscope $end
     $upscope $end
     $scope module gen_synapses[1] $end
      $scope module synapse $end
       $var wire 32 f DATA_WIDTH [31:0] $end
       $var wire 6 h WEIGHT [5:0] $end
       $var wire 6 i RESET_WEIGHT [5:0] $end
       $var wire 1 . inSpike $end
       $var wire 6 M weight [5:0] $end
      $upscope $end
     $upscope $end
     $scope module gen_synapses[2] $end
      $scope module synapse $end
       $var wire 32 f DATA_WIDTH [31:0] $end
       $var wire 6 h WEIGHT [5:0] $end
       $var wire 6 i RESET_WEIGHT [5:0] $end
       $var wire 1 1 inSpike $end
       $var wire 6 N weight [5:0] $end
      $upscope $end
     $upscope $end
     $scope module gen_synapses[3] $end
      $scope module synapse $end
       $var wire 32 f DATA_WIDTH [31:0] $end
       $var wire 6 h WEIGHT [5:0] $end
       $var wire 6 i RESET_WEIGHT [5:0] $end
       $var wire 1 4 inSpike $end
       $var wire 6 O weight [5:0] $end
      $upscope $end
     $upscope $end
     $scope module neuron $end
      $var wire 32 g DATA_WIDTH [31:0] $end
      $var wire 8 j THRESHOLD [7:0] $end
      $var wire 8 k LEAK [7:0] $end
      $var wire 8 l RESET_POTENTIAL [7:0] $end
      $var wire 1 ` clk $end
      $var wire 1 a resetn $end
      $var wire 8 \ inWeight [7:0] $end
      $var wire 1 4 outSpike $end
      $var wire 8 ] membranePotential [7:0] $end
      $var wire 1 ^ nextSpike $end
      $var wire 8 _ nextPotential [7:0] $end
     $upscope $end
    $upscope $end
   $upscope $end
  $upscope $end
 $upscope $end
$enddefinitions $end


#0
b0000 "
b0000 #
b0000 $
0%
0&
0'
0(
0)
b00000000000000000000000000000000 *
0+
0,
b00000000000000000000000000000000 -
0.
0/
b00000000000000000000000000000000 0
01
02
b00000000000000000000000000000000 3
04
05
b00000000000000000000000000000000 6
b000000 7
b000000 8
b000000 9
b000000 :
b000000 ;
b000000 <
b000000 =
b000000 >
b000000 ?
b000000 @
b000000 A
b000000 B
b000000 C
b000000 D
b000000 E
b000000 F
b00000000 G
b00000000 H
b00000000 I
b00000000 J
0K
b000000 L
b000000 M
b000000 N
b000000 O
b00000000 P
b00000000 Q
0R
b00000000 S
b00000000 T
b00000000 U
0V
b00000000 W
b00000000 X
b00000000 Y
0Z
b00000000 [
b00000000 \
b00000000 ]
0^
b00000000 _
0`
0a
1b
b00000000000000000000000000000101 c
b00000000000000000000000000001010 d
b00000000000000000000000000000100 e
b00000000000000000000000000000110 f
b00000000000000000000000000001000 g
b001000 h
b000000 i
b00100000 j
b00000001 k
b00000000 l
#5000
b1111 "
1%
1'
1(
1)
1,
1/
12
15
1`
#10000
0`
#15000
1`
#20000
0`
#25000
1`
#30000
0`
#35000
1`
#40000
0`
#45000
1`
1a
#50000
0`
#55000
1`
#60000
0`
#65000
1`
#70000
0`
#75000
1`
#80000
0`
#85000
1`
#90000
0`
#95000
0(
1`
0b
#100000
0`
#105000
0)
1`
#110000
0`
#115000
b00000000000000000000000000000001 *
1`
#120000
0`
#125000
b00000000000000000000000000000010 *
1`
#130000
0`
#135000
b00000000000000000000000000000011 *
1`
#140000
0`
#145000
b00000000000000000000000000000100 *
1`
#150000
0`
#155000
0'
b00000000000000000000000000000000 *
1`
#160000
0`
#165000
b0001 #
0%
1&
b001000 7
b001000 ;
b001000 ?
b001000 C
b00001000 G
b00001000 H
b00001000 I
b00001000 J
1K
b001000 L
b00001000 P
b00001000 S
b00001000 T
b00001000 W
b00001000 X
b00001000 [
b00001000 \
b00001000 _
1`
#170000
0`
#175000
b0000 #
0&
b000000 7
b000000 ;
b000000 ?
b000000 C
b00000000 G
b00000000 H
b00000000 I
b00000000 J
0K
b000000 L
b00000000 P
b00001000 Q
b00000111 S
b00000000 T
b00001000 U
b00000111 W
b00000000 X
b00001000 Y
b00000111 [
b00000000 \
b00001000 ]
b00000111 _
1`
#180000
0`
#185000
b00000111 Q
b00000110 S
b00000111 U
b00000110 W
b00000111 Y
b00000110 [
b00000111 ]
b00000110 _
1`
#190000
0`
#195000
1(
b00000110 Q
b00000101 S
b00000110 U
b00000101 W
b00000110 Y
b00000101 [
b00000110 ]
b00000101 _
1`
1b
#200000
0`
#205000
1)
b00000101 Q
b00000100 S
b00000101 U
b00000100 W
b00000101 Y
b00000100 [
b00000101 ]
b00000100 _
1`
#210000
0`
#215000
b00000000000000000000000000000001 *
b00000100 Q
b00000011 S
b00000100 U
b00000011 W
b00000100 Y
b00000011 [
b00000100 ]
b00000011 _
1`
#220000
0`
#225000
b00000000000000000000000000000010 *
b00000011 Q
b00000010 S
b00000011 U
b00000010 W
b00000011 Y
b00000010 [
b00000011 ]
b00000010 _
1`
#230000
0`
#235000
b00000000000000000000000000000011 *
b00000010 Q
b00000001 S
b00000010 U
b00000001 W
b00000010 Y
b00000001 [
b00000010 ]
b00000001 _
1`
#240000
0`
#245000
b00000000000000000000000000000100 *
b00000001 Q
b00000000 S
b00000001 U
b00000000 W
b00000001 Y
b00000000 [
b00000001 ]
b00000000 _
1`
#250000
0`
#255000
1'
b00000000000000000000000000000000 *
b00000000 Q
b00000000 U
b00000000 Y
b00000000 ]
1`
#260000
0`
#265000
1%
1`
